README
setup.py
pypq/__init__.py
pypq/connection.py
pypq/constants.py
pypq/cursor.py
pypq/datatypes.py
pypq/dbapi.py
pypq/errors.py
pypq/libpq.py
pypq.egg-info/PKG-INFO
pypq.egg-info/SOURCES.txt
pypq.egg-info/dependency_links.txt
pypq.egg-info/top_level.txt
pypq/django_backend/__init__.py
pypq/django_backend/base.py
pypq/django_backend/introspection.py
pypq/django_backend/south_adapter.py