Metadata-Version: 1.0
Name: pypq
Version: 0.1.2
Summary: Python PostgreSQL DBAPI 2.0 compliant driver using ctypes and libpq.so, works with PyPy
Home-page: https://bitbucket.org/descent/pypq
Author: Igor Katson
Author-email: igor.katson@gmail.com
License: UNKNOWN
Platform: UNKNOWN
Classifier: Development Status :: 3 - Alpha
Classifier: Intended Audience :: Developers
Classifier: License :: OSI Approved :: GNU General Public License (GPL)
Classifier: Operating System :: POSIX
Classifier: Programming Language :: Python
Classifier: Topic :: Database
Classifier: Topic :: Database :: Front-Ends
Classifier: Topic :: Software Development :: Libraries :: Python Modules
